{
    "odds": [
        {
            "player": "Walker Kessler",
            "team": "Washington Wizards",
            "opponent": "Utah Jazz",
            "stat_type": "Points",
            "line": 25,
            "over_odds": -120,
            "under_odds": -120
        },
        {
            "player": "Anthony Edwards",
            "team": "Minnesota Timberwolves",
            "opponent": "Denver Nuggets",
            "stat_type": "Assists",
            "line": 4.5,
            "over_odds": -125,
            "under_odds": -130
        },
        {
            "player": "Chet Holmgren",
            "team": "Oklahoma City Thunder",
            "opponent": "Utah Jazz",
            "stat_type": "Points",
            "line": 28.5,
            "over_odds": -110,
            "under_odds": -110
        },
        {
            "player": "Devin Vassell",
            "team": "San Antonio Spurs",
            "opponent": "Houston Rockets",
            "stat_type": "Points",
            "line": 4.5,
            "over_odds": -138,
            "under_odds": -138
        },
        {
            "player": "OG Anunoby",
            "team": "San Antonio Spurs",
            "opponent": "Houston Rockets",
            "stat_type": "Points",
            "line": 4.5,
            "over_odds": -138,
            "under_odds": -138
        }
    ]
}